zipgit/__init__.py
zipgit/cli.py
zipgit-1.0.0.dist-info/licenses/LICENSE
zipgit-1.0.0.dist-info/WHEEL
zipgit-1.0.0.dist-info/entry_points.txt
zipgit-1.0.0.dist-info/METADATA
zipgit-1.0.0.dist-info/RECORD
