Metadata-Version: 2.4
Name: zipgit
Version: 1.0.0
Summary: CLI tool for zipping a git repo and excluding .gitignore and untracked files
Author: Phill Johntony
Author-email: Phill Johntony <pdjohntony@gmail.com>
License-Expression: MIT
License-File: LICENSE
Classifier: Programming Language :: Python :: 3
Classifier: Operating System :: OS Independent
Requires-Dist: pathspec>=1.0.4
Requires-Dist: rich>=14.3.1
Requires-Dist: typer>=0.21.1
Requires-Python: >=3.13
Project-URL: Homepage, https://github.com/pdjohntony/zipgit
Project-URL: Issues, https://github.com/pdjohntony/zipgit/issues
